aisetup/__init__.py
aisetup-0.1.9.dist-info/METADATA
aisetup-0.1.9.dist-info/WHEEL
aisetup-0.1.9.dist-info/RECORD
